{
  "products": [
    {
      "id": 1737980206435,
      "name": "管子",
      "price": "23",
      "category": "1",
      "stock": "23",
      "priceUnit": "元/米",
      "stockUnit": "根",
      "description": "gterhrth海染套会",
      "addTime": "2025-01-27T12:16:46.435Z",
      "image": "https://pic.jlon.top/i/2025/01/27/xcjoms-0.png"
    },
    {
      "id": 1737981879471,
      "name": "1231",
      "price": "12",
      "category": "图书",
      "stock": "23",
      "priceUnit": "￥",
      "stockUnit": "个",
      "description": "gferg",
      "addTime": "2025-01-27T12:44:39.471Z",
      "image": "https://pic.jlon.top/i/2025/01/27/xt6htp-0.png"
    },
    {
      "id": 1737987777653,
      "name": "三大高手",
      "price": "2",
      "category": "图书",
      "stock": "213",
      "priceUnit": "元/米",
      "stockUnit": "根",
      "description": "fewfger",
      "addTime": "2025-01-27T14:22:57.653Z",
      "image": "https://pic.jlon.top/i/2025/01/27/10r9hax-0.png"
    }
  ],
  "lastUpdate": "2025-01-27T14:56:32.627Z",
  "version": "1.0"
}